eztv.py
eztv.py-2025.9.25.data/scripts/eztv.py
eztv.py-2025.9.25.dist-info/LICENSE
eztv.py-2025.9.25.dist-info/METADATA
eztv.py-2025.9.25.dist-info/WHEEL
eztv.py-2025.9.25.dist-info/top_level.txt
eztv.py-2025.9.25.dist-info/RECORD
